LICENSE
MANIFEST.in
README.md
requirements.txt
setup.py
opsview/__init__.py
opsview/opsview.py
opsview.egg-info/PKG-INFO
opsview.egg-info/SOURCES.txt
opsview.egg-info/dependency_links.txt
opsview.egg-info/requires.txt
opsview.egg-info/top_level.txt