Metadata-Version: 1.1
Name: opsview
Version: 0.9.0
Summary: Opsview REST API client
Home-page: https://github.com/pschmitt/python-opsview
Author: Philipp Schmitt
Author-email: philipp@schmitt.co
License: GPLv3
Keywords: opsview,monitoring,rest,client
Platform: UNKNOWN
Classifier: License :: OSI Approved :: GNU General Public License v3 (GPLv3)
